{
    "description": "DO NOT DELETE THIS FILE. This file is used to keep track of which files have been synced in the most recent deployment. If you delete this file a resync will need to be done (which can take a while) - read more: https://github.com/SamKirkland/FTP-Deploy-Action",
    "version": "1.0.0",
    "generatedTime": 1757047905714,
    "data": [
        {
            "type": "file",
            "name": "package.json",
            "size": 1185,
            "hash": "65760fbf35abcd4d0c3043790606cf19604f119ff5f221fad5a282554376cb03"
        },
        {
            "type": "folder",
            "name": "pb_public"
        },
        {
            "type": "folder",
            "name": "pb_migrations"
        },
        {
            "type": "folder",
            "name": "pb_hooks"
        },
        {
            "type": "file",
            "name": "pb_public/og-image.png",
            "size": 97898,
            "hash": "62372f6ca94928ce68bc7321b2185e493b979d074b87a9e078a27f3c8a8b9f14"
        },
        {
            "type": "file",
            "name": "pb_public/favicon.ico",
            "size": 131070,
            "hash": "eade4d177060fc5f49cee53a4a1cc1d3e757de60ba8178c568465cd2b4436ebe"
        },
        {
            "type": "file",
            "name": "pb_migrations/1757042216_updated_blogposts.js",
            "size": 677,
            "hash": "aa1ca8b6d3b577c915ebd8baabb8ed8870cd8ea126633eeec4af456b74e22023"
        },
        {
            "type": "file",
            "name": "pb_hooks/pocketpages.pb.js",
            "size": 23,
            "hash": "83f80163c8424e9245990124ea42a8b74425828cf66395cb680498225d26f275"
        },
        {
            "type": "folder",
            "name": "pb_hooks/pages"
        },
        {
            "type": "folder",
            "name": "pb_hooks/pages/sitemap.xml"
        },
        {
            "type": "folder",
            "name": "pb_hooks/pages/robots.txt"
        },
        {
            "type": "file",
            "name": "pb_hooks/pages/app.tailwind.css",
            "size": 59,
            "hash": "cc1a7ad0d019ddb1d32d0ecb588ba0ac26ce41d8625dd6c366348b25f83a28ec"
        },
        {
            "type": "file",
            "name": "pb_hooks/pages/app.css",
            "size": 60783,
            "hash": "a0db9a8db29961549e8fdb7f0b4f8d9abd77c8b49b5cddf668ab14ba508f8738"
        },
        {
            "type": "file",
            "name": "pb_hooks/pages/+middleware.js",
            "size": 1546,
            "hash": "749ee1cfbc34c8374fd197e1b0f5371711e9f4eed9ab4ff857670810f44a1f99"
        },
        {
            "type": "file",
            "name": "pb_hooks/pages/+config.js",
            "size": 384,
            "hash": "dbb9881f76173ec44d6e5955c0a9554a67bb65e4f715ea5a6b6b43a79cc0de03"
        },
        {
            "type": "folder",
            "name": "pb_hooks/pages/(navbarLayout)"
        },
        {
            "type": "file",
            "name": "pb_hooks/pages/sitemap.xml/index.ejs",
            "size": 766,
            "hash": "9b1542afb1d62d67e6c18ebbd000ee857e5bf03692d7dc99a21aa95f63e177ff"
        },
        {
            "type": "file",
            "name": "pb_hooks/pages/robots.txt/index.ejs",
            "size": 47,
            "hash": "26e7825e4092406121d1ec381db0568bef8f636ecd03cc129761de5f391c2ffb"
        },
        {
            "type": "file",
            "name": "pb_hooks/pages/(navbarLayout)/index.ejs",
            "size": 681,
            "hash": "5ad6322fe4762b30709b467ad2760a38821cba0f004cd49c9ae6e51f89198d90"
        },
        {
            "type": "folder",
            "name": "pb_hooks/pages/(navbarLayout)/blog"
        },
        {
            "type": "folder",
            "name": "pb_hooks/pages/(navbarLayout)/_private"
        },
        {
            "type": "file",
            "name": "pb_hooks/pages/(navbarLayout)/+layout.ejs",
            "size": 4637,
            "hash": "56f404c14ec96041c282d40444b377eb47eb882b1423e3ec213ab45ff48aa07f"
        },
        {
            "type": "folder",
            "name": "pb_hooks/pages/(navbarLayout)/blog/posts"
        },
        {
            "type": "file",
            "name": "pb_hooks/pages/(navbarLayout)/blog/index.ejs",
            "size": 31,
            "hash": "7f7647f4157b4ab3dc33787299c8d703feb80863b2f59ff2ca18cc4a9c093ea9"
        },
        {
            "type": "file",
            "name": "pb_hooks/pages/(navbarLayout)/blog/posts/[postId].ejs",
            "size": 708,
            "hash": "5c09506302d379d553062d829e1d97799a9fd208f0e2c733d3c6a03fb762425b"
        },
        {
            "type": "file",
            "name": "pb_hooks/pages/(navbarLayout)/_private/blogpage.ejs",
            "size": 267,
            "hash": "ad57a31346192383ee466623065c5049bd947f3913c996a34066211040269cca"
        },
        {
            "type": "file",
            "name": "pb_hooks/pages/(navbarLayout)/_private/blogcard.ejs",
            "size": 2129,
            "hash": "c573ffbbc502039c858a29418333c73087288b708ac2cdf7259246633dc7e393"
        }
    ]
}