{
    "description": "DO NOT DELETE THIS FILE. This file is used to keep track of which files have been synced in the most recent deployment. If you delete this file a resync will need to be done (which can take a while) - read more: https://github.com/SamKirkland/FTP-Deploy-Action",
    "version": "1.0.0",
    "generatedTime": 1756880343856,
    "data": [
        {
            "type": "file",
            "name": "package.json",
            "size": 909,
            "hash": "f0bedf0bf3fcf38b0b3d7d7b14fe02817d5b9a2373c22a70ed2c78c4bb5d30c6"
        },
        {
            "type": "folder",
            "name": "pb_hooks"
        },
        {
            "type": "file",
            "name": "pb_hooks/pocketpages.pb.js",
            "size": 23,
            "hash": "83f80163c8424e9245990124ea42a8b74425828cf66395cb680498225d26f275"
        },
        {
            "type": "folder",
            "name": "pb_hooks/pages"
        },
        {
            "type": "file",
            "name": "pb_hooks/pages/index.ejs",
            "size": 486,
            "hash": "b739a3ec4dce64b7cbc350939a92b6a91eccb23d0668a0e6d016f84cc0262a8e"
        },
        {
            "type": "folder",
            "name": "pb_hooks/pages/blogs"
        },
        {
            "type": "file",
            "name": "pb_hooks/pages/app.tailwind.css",
            "size": 59,
            "hash": "cc1a7ad0d019ddb1d32d0ecb588ba0ac26ce41d8625dd6c366348b25f83a28ec"
        },
        {
            "type": "file",
            "name": "pb_hooks/pages/app.css",
            "size": 55378,
            "hash": "13322804a702e6e3d26bc252f1621015aed9b548c049c64a2c3774cdf5e8b3ad"
        },
        {
            "type": "file",
            "name": "pb_hooks/pages/+layout.ejs",
            "size": 2488,
            "hash": "d2b5afc5e21f200c6ab9579b263280bebdb7ff75b7654011155d1ca010b6ba0f"
        },
        {
            "type": "file",
            "name": "pb_hooks/pages/blogs/index.ejs",
            "size": 279,
            "hash": "c63719d7a8805548eb0de721b8fedd9d8ceeae42d9a55dc35b7f9ddb0690a508"
        }
    ]
}